langai/__init__.py
langai/client.py
langai_client/__init__.py
langai_client/client.py
langai_client-0.0.1.dist-info/DESCRIPTION.rst
langai_client-0.0.1.dist-info/METADATA
langai_client-0.0.1.dist-info/RECORD
langai_client-0.0.1.dist-info/WHEEL
langai_client-0.0.1.dist-info/metadata.json
langai_client-0.0.1.dist-info/top_level.txt
