Metadata-Version: 2.0
Name: langai-client
Version: 0.0.1
Summary: A LangAI API client written in Python.
Home-page: https://github.com/lang-ai/langai-python
Author: Lang.ai
Author-email: info@lang.ai
License: MIT
Keywords: lang.ai api client
Platform: UNKNOWN
Classifier: Programming Language :: Python :: 3
Classifier: License :: OSI Approved :: MIT License
Classifier: Operating System :: OS Independent
